grahamscandelaunay/__init__.py
grahamscandelaunay/grahamscandelaunay.py
grahamscandelaunay/point.py
grahamscandelaunay/visual.py
graham_scan_based_incremental_delaunay-1.0.1.dist-info/LICENSE
graham_scan_based_incremental_delaunay-1.0.1.dist-info/METADATA
graham_scan_based_incremental_delaunay-1.0.1.dist-info/WHEEL
graham_scan_based_incremental_delaunay-1.0.1.dist-info/top_level.txt
graham_scan_based_incremental_delaunay-1.0.1.dist-info/RECORD
