Metadata-Version: 2.1
Name: graham-scan-based-incremental-delaunay
Version: 1.0.1
Summary: Graham-scan based incremental Delaunay triangulation algorithm with visualization.
Home-page: https://github.com/carlklier/graham-scan-based-incremental-delaunay
Author: Carl Klier, Jimmy Zheng, Zhikai Gao
License: MIT license
Platform: UNKNOWN
Requires-Dist: numpy (>=1.19.0)
Requires-Dist: pyglet (>=1.5.0)
